azure_recommendations_8/__init__.py
azure_recommendations_8/recommendation/__init__.py
azure_recommendations_8/recommendation/advisor_recommendations.py
azure_recommendations_8/recommendation/network_recommendations.py
azure_recommendations_8/recommendation/utils.py
azure_recommendations_8/recommendation/vm_recommendations.py
azure_recommendations_8-0.1.8.dist-info/LICENCE
azure_recommendations_8-0.1.8.dist-info/METADATA
azure_recommendations_8-0.1.8.dist-info/WHEEL
azure_recommendations_8-0.1.8.dist-info/top_level.txt
azure_recommendations_8-0.1.8.dist-info/RECORD
